{
  "name": "dotfiles Development",
  "build": {
    "dockerfile": "Dockerfile",
    "context": ".."
  },
  "features": {
    "ghcr.io/devcontainers/features/common-utils:2": {
      "installZsh": true,
      "configureZshAsDefaultShell": true,
      "installOhMyZsh": true,
      "upgradePackages": true
    },
    "ghcr.io/devcontainers/features/git:1": {},
    "ghcr.io/devcontainers/features/github-cli:1": {}
  },
  "customizations": {
    "vscode": {
      "settings": {
        "terminal.integrated.defaultProfile.linux": "zsh",
        "terminal.integrated.fontFamily": "JetBrains Mono",
        "editor.fontFamily": "JetBrains Mono, monospace",
        "editor.fontSize": 14
      },
      "extensions": [
        "foxundermoon.shell-format",
        "timonwong.shellcheck",
        "mads-hartmann.bash-ide-vscode",
        "EditorConfig.EditorConfig",
        "yzhang.markdown-all-in-one"
      ]
    }
  },
  "postCreateCommand": "bash .devcontainer/post-create.sh",
  "postStartCommand": "zsh",
  "remoteUser": "vscode",
  "mounts": [
    "source=${localWorkspaceFolder},target=/home/vscode/dotfiles,type=bind,consistency=cached"
  ],
  "workspaceFolder": "/home/vscode/dotfiles",
  "forwardPorts": [],
  "portsAttributes": {},
  "containerEnv": {
    "DOTFILES_DEV": "true"
  }
}
